CHANGELOG.md
affine-stubs/__init__.pyi
types_affine-0.1.0.dist-info/LICENSE
types_affine-0.1.0.dist-info/WHEEL
types_affine-0.1.0.dist-info/METADATA
types_affine-0.1.0.dist-info/RECORD
