Metadata-Version: 2.1
Name: types-affine
Version: 0.1.0
Summary: Types for the Affine package
Home-page: https://github.com/kylebarron/types-affine
License: MIT
Author: Kyle Barron
Author-email: kylebarron2@gmail.com
Requires-Python: >=3.6.1,<4.0.0
Classifier: License :: OSI Approved :: MIT License
Classifier: Programming Language :: Python :: 3
Classifier: Programming Language :: Python :: 3.7
Classifier: Programming Language :: Python :: 3.8
Classifier: Programming Language :: Python :: 3.9
Project-URL: Repository, https://github.com/kylebarron/types-affine
